py_watch_power/__init__.py
py_watch_power/__version__.py
py_watch_power/cli.py
py_watch_power/core/__init__.py
py_watch_power/core/cli.py
py_watch_power/core/dto.py
py_watch_power/core/inverter.py
py_watch_power/core/protocol.py
py_watch_power/core/utils.py
py_watch_power/py.typed
pywatchpower-1.0.0.dist-info/LICENSE
pywatchpower-1.0.0.dist-info/METADATA
pywatchpower-1.0.0.dist-info/WHEEL
pywatchpower-1.0.0.dist-info/entry_points.txt
pywatchpower-1.0.0.dist-info/RECORD
