Metadata-Version: 2.1
Name: pywatchpower
Version: 1.0.0
Summary: 
Home-page: https://github.com/cchangelabs/py-watch-power
License: GPL-3.0
Keywords: inverter,solar,power,watchpower,msx,mks,axioma,axpert,mppsolar,voltronic,voltacon,effecta
Author: Dmitry Berezovsky
Maintainer: Dmitry Berezovsky
Requires-Python: >=3.11,<4.0
Classifier: Development Status :: 3 - Alpha
Classifier: Intended Audience :: Developers
Classifier: License :: OSI Approved :: GNU General Public License v3 (GPLv3)
Classifier: License :: OSI Approved :: GNU General Public License v3 or later (GPLv3+)
Classifier: Operating System :: OS Independent
Classifier: Programming Language :: Python :: 3
Classifier: Programming Language :: Python :: 3.11
Classifier: Topic :: Software Development :: Libraries :: Python Modules
Provides-Extra: hass-mqtt
Requires-Dist: cli-rack (>=1.0.6,<1.1.0)
Requires-Dist: hid (>=1.0.6,<1.1.0)
Requires-Dist: paho-mqtt (>=2.1,<3.0) ; extra == "hass-mqtt"
Project-URL: Repository, https://github.com/cchangelabs/py-watch-power
